sc2image/__init__.py
sc2image/dataset.py
sc2image/version.py
sc2image/utils/__init__.py
sc2image/utils/metadata_processing.py
sc2image/utils/sensor_utils.py
sc2image/utils/unit_type_data.py
sc2image-1.0.4.dist-info/LICENSE
sc2image-1.0.4.dist-info/METADATA
sc2image-1.0.4.dist-info/WHEEL
sc2image-1.0.4.dist-info/top_level.txt
sc2image-1.0.4.dist-info/RECORD
