Metadata-Version: 2.1
Name: sc2image
Version: 1.0.4
Summary: The StarCraft Image dataset
Home-page: https://starcraftdata.davidinouye.com/
Author: StarCraftImage team
Author-email: dinouye@purdue.edu
License: MIT
Platform: UNKNOWN
Classifier: Topic :: Scientific/Engineering :: Artificial Intelligence
Classifier: Intended Audience :: Science/Research
Classifier: Programming Language :: Python :: 3
Classifier: License :: OSI Approved :: MIT License
Requires-Python: >=3.7
License-File: LICENSE
Requires-Dist: torch (>=1.7.0)
Requires-Dist: numpy (>=1.19.1)
Requires-Dist: tqdm (>=4.53.0)
Requires-Dist: torchvision (>=0.8.2)
Requires-Dist: outdated (>=0.2.0)
Requires-Dist: pandas (>=1.1.0)
Requires-Dist: pillow (>=7.2.0)
Requires-Dist: tqdm (>=4.6.0)
